CHANGES.txt
LICENSE.txt
MANIFEST.in
README.md
setup.cfg
setup.py
deepCR/__init__.py
deepCR/dataset.py
deepCR/evaluate.py
deepCR/model.py
deepCR/parts.py
deepCR/parts_batchnorm.py
deepCR/training.py
deepCR/unet.py
deepCR/unet_batchnorm.py
deepCR/util.py
deepCR/test/__init__.py
deepCR/test/test_dataset.py
deepCR/test/test_evaluate.py
deepCR/test/test_model.py
deepCR/test/test_train.py
deepCR/test/test_util.py
docs/Makefile
docs/conf.py
docs/deepCR.rst
docs/deepCR.test.rst
docs/environment.yml
docs/index.rst
docs/make.bat
docs/model_zoo.rst
docs/modules.rst
docs/requirements.txt
docs/tutorial_train.rst
docs/tutorial_use.rst
imgs/acs_wfc_f606w_roc.png
imgs/decam_v1.png
imgs/network.png
imgs/postage-sm.jpg
learned_models/__init__.py
learned_models/inpaint/ACS-WFC-F606W-2-32.pth
learned_models/inpaint/ACS-WFC-F606W-3-32.pth
learned_models/mask/ACS-WFC-F435W.pth
learned_models/mask/ACS-WFC-F606W-2-4.pth
learned_models/mask/ACS-WFC-F606W.pth
learned_models/mask/ACS-WFC-F814W.pth
learned_models/mask/ACS-WFC.pth
learned_models/mask/WFC3-UVIS.pth
learned_models/mask/decam.pth
learned_models/mask/example_model.pth