Metadata-Version: 2.1
Name: deepCR
Version: 0.3.1
Home-page: http://pypi.python.org/pypi/deepCR/
Author: Keming Zhang
Author-email: kemingz@berkeley.edu
License: BSD 3-Clause
Classifier: Development Status :: 4 - Beta
Classifier: Environment :: Console
Classifier: Intended Audience :: Science/Research
Classifier: License :: OSI Approved :: BSD License
Classifier: Operating System :: POSIX
Classifier: Programming Language :: Python :: 3.5
Classifier: Programming Language :: Python :: 3.6
Classifier: Programming Language :: Python :: 3.7
Classifier: Topic :: Internet
Classifier: Topic :: Scientific/Engineering :: Astronomy
Requires-Python: >=3.5
License-File: LICENSE.txt
